i3altlayout/__init__.py
i3altlayout/i3altlayout.py
i3altlayout-1.1.4.dist-info/LICENSE
i3altlayout-1.1.4.dist-info/METADATA
i3altlayout-1.1.4.dist-info/WHEEL
i3altlayout-1.1.4.dist-info/entry_points.txt
i3altlayout-1.1.4.dist-info/top_level.txt
i3altlayout-1.1.4.dist-info/RECORD
